rith/__init__.py
rith/application.py
rith/endpoint.py
rith/errors.py
rith/geometry.py
rith/permissions.py
rith/responses.py
rith/utilities.py
rith-0.0.1.dist-info/LICENSE
rith-0.0.1.dist-info/METADATA
rith-0.0.1.dist-info/WHEEL
rith-0.0.1.dist-info/top_level.txt
rith-0.0.1.dist-info/RECORD
