Metadata-Version: 2.1
Name: rith
Version: 0.0.1
Summary: An open-source geospatial API
Home-page: https://github.com/joshuapowell/arith
Author: Joshua Powell
Author-email: UNKNOWN
License: MIT
Keywords: python geospatial location api
Platform: UNKNOWN
Requires-Dist: flask
Requires-Dist: flask-security
Requires-Dist: flask-restless
Requires-Dist: flask-sqlalchemy
Requires-Dist: geoalchemy2
Requires-Dist: flask-oauthlib
Requires-Dist: requests
Requires-Dist: psycopg2
